ns_ab_test_sdk/__init__.py
ns_ab_test_sdk/ns_ab_test_sdk.py
ns_ab_test_sdk-0.1.1.dist-info/METADATA
ns_ab_test_sdk-0.1.1.dist-info/WHEEL
ns_ab_test_sdk-0.1.1.dist-info/top_level.txt
ns_ab_test_sdk-0.1.1.dist-info/RECORD
