Metadata-Version: 2.1
Name: ns-ab-test-sdk
Version: 0.1.1
Summary: A simple A/B testing SDK for recording and saving data
Author: nobody
Author-email: nobody@example.com
Classifier: Programming Language :: Python :: 3
Classifier: License :: OSI Approved :: MIT License
Classifier: Operating System :: OS Independent
Requires-Python: >=3
